neural_transport/__init__.py
neural_transport/datamodule.py
neural_transport/litmodule.py
neural_transport-0.0.2.dist-info/LICENSE
neural_transport-0.0.2.dist-info/METADATA
neural_transport-0.0.2.dist-info/WHEEL
neural_transport-0.0.2.dist-info/top_level.txt
neural_transport-0.0.2.dist-info/RECORD
