Metadata-Version: 2.1
Name: neural_transport
Version: 0.0.2
Summary: Neural Transport - A Python library to train neural network emulators of atmospheric transport models.
Author-email: Vitus Benson <vbenson@bgc-jena.mpg.de>
License: MIT License
Project-URL: Repository, https://github.com/vitusbenson/neural_transport.git
Project-URL: Issues, https://github.com/vitusbenson/neural_transport/issues
Keywords: AI,neural network,transport model,carbon,co2,emulator,pytorch
Requires-Python: >=3.10
License-File: LICENSE
Requires-Dist: numpy
Requires-Dist: xarray
Requires-Dist: dask
Requires-Dist: ecmwf-api-client
Requires-Dist: tqdm
Requires-Dist: xesmf
Requires-Dist: cdo
Requires-Dist: numcodecs
Requires-Dist: zarr
Requires-Dist: pandas
Requires-Dist: xskillscore
Requires-Dist: tensorboard
Requires-Dist: torch
Requires-Dist: cartopy
Requires-Dist: matplotlib
Requires-Dist: seaborn
Requires-Dist: xrft
Requires-Dist: xmovie
Requires-Dist: torch_geometric
Requires-Dist: scipy
Requires-Dist: trimesh
Requires-Dist: tensorly
Requires-Dist: torch_harmonics
Requires-Dist: timm
Requires-Dist: einops
Requires-Dist: pyarrow
Requires-Dist: h5netcdf
Requires-Dist: netcdf4
